{
  "users": [
    {
      "id": 1,
      "username": "JohnL",
      "password": "asd",
      "firstName": "John",
      "lastName": "LeBlanc",
      "email": "john.leblanc03@gmail.com"
    }
  ],
  "clients": [
    {
      "id": 1,
      "userID": 1,
      "firstName": "Jane",
      "lastName": "Doe",
      "jobTitle": "CEO",
      "company": "RealCo",
      "email": "jane@realco.ca",
      "phone": "613-440-4141",
      "addressStreet": "22 Third Ave",
      "addressCity": "Kingston",
      "addressProvince": "ON",
      "addressPostalCode": "K7M 9J0",
      "addressCountry": "Canada"
    },
    {
      "id": 2,
      "userID": 1,
      "firstName": "John",
      "lastName": "Smith",
      "jobTitle": "Web Developer",
      "company": "FakeCo",
      "email": "john@fakeco.ca",
      "phone": "613-440-4141",
      "addressStreet": "22 Third Ave",
      "addressCity": "Kingston",
      "addressProvince": "ON",
      "addressPostalCode": "K7M 9J0",
      "addressCountry": "Canada"
    },
    {
      "userID": 1,
      "firstName": "Adam",
      "lastName": "Savage",
      "jobTitle": "Inventor",
      "email": "adam.savage@mythbustors.com",
      "phone": "---",
      "company": "Myth Busters",
      "addressStreet": "12 Main",
      "addressPostalCode": "K1B 9B0",
      "addressProvince": "NY",
      "addressCountry": "United States",
      "id": 3
    },
    {
      "userID": 1,
      "firstName": "Zagreus",
      "lastName": "Son of Hades",
      "jobTitle": "Prince",
      "email": "zag@hotmail.com",
      "phone": "666-666-6661",
      "company": "Underworld",
      "addressStreet": "House of Hades",
      "addressPostalCode": "H3L 1O0",
      "addressProvince": "H",
      "addressCountry": "None",
      "id": 4
    },
    {
      "firstName": "Johnathan",
      "lastName": "LeBlanc",
      "jobTitle": "Designer",
      "email": "john.leblanc03@gmail.com",
      "phone": "6134498060",
      "company": "a",
      "addressStreet": "59 Coventry Crescent",
      "addressCity": "Kingston",
      "addressPostalCode": "K7M 7S8",
      "addressProvince": "Ontario",
      "addressCountry": "Canada",
      "id": 5
    }
  ],
  "projects": [
    {
      "id": 1,
      "userID": 1,
      "clientID": 1,
      "title": "Database Structure",
      "description": "Create a structure for the database.",
      "status": "COMPLETE",
      "startTime": "2021/03/01/1200"
    },
    {
      "id": 2,
      "userID": 1,
      "clientID": 2,
      "title": "Project Manager",
      "description": "Build out the Project Manager web application.",
      "status": "INCOMPLETE",
      "startTime": "2021/03/01/1200"
    }
  ],
  "tasks": [
    {
      "id": 1,
      "projectID": 2,
      "title": "Table",
      "description": "Create a table component.",
      "status": "INCOMPLETE",
      "chargeType": "HOURLY",
      "rate": 75
    }
  ],
  "time-logs": [
    {
      "id": 1,
      "taskID": 1,
      "startTime": "2021/03/09/1309",
      "endTime": ""
    }
  ],
  "invoices": [
    {
      "id": 1,
      "projectID": 1,
      "clientID": 1,
      "date": "2021/03/09",
      "status": "SENT",
      "totalBill": 100
    }
  ]
}